ddtols/__init__.py
ddtols/decorators.py
ddtols/diary.py
ddtols/main.py
ddtols/py.typed
ddtols/scheduler.py
ddtols/cipher/__init__.py
ddtols/cipher/aes.py
ddtols/cipher/rsa.py
ddtols/jsenv/__init__.py
ddtols/jsenv/executor.py
ddtols-0.1.7.dist-info/licenses/LICENSE
ddtols-0.1.7.dist-info/METADATA
ddtols-0.1.7.dist-info/WHEEL
ddtols-0.1.7.dist-info/top_level.txt
ddtols-0.1.7.dist-info/RECORD
